[
    {
      "title": "走行・投球フォームの映像データに基づく解析",
      "path": "pdf/走行・投球フォームの映像データに基づく解析.pdf",
      "description": "データサイエンス実験B(大草)",
      "tags": ["データサイエンス実験B","実験", "データサイエンス", "スポーツ", "OpenPose"]
    },
    {
        "title": "Flaskアプリの概要",
        "path": "pdf/Flaskアプリの概要.pdf",
        "description": "Flaskアプリ構成の説明です。",
        "tags": ["Flask", "アプリ", "スライド"]
      },
      {
        "title": "ボストンの犯罪率分関モデル",
        "path": "pdf/ボストンの犯罪率分析モデル.pdf",
        "description": "データ解析第二での発表スライドです。",
        "tags": ["データ解析第二", "発表", "スライド", "ボストン", "犯罪率","機械学習"]
      },
      {
        "title": "交通最適化ソリューション",
        "path": "pdf/交通最適化ソリューション.pdf",
        "description": "ビジネス案についてのスライドです。",
        "tags": ["ビジネス案", "スライド", "交通最適化", "ソリューション","データサイエンス実験B"]
      },
    {
        "title": "1on1forEngineer自己紹介",
        "path": "pdf/1on1forEngineer_髙木悠人_中央大学.pdf",
        "description": "自己紹介用スライドです。",
        "tags": ["自己紹介", "1on1forEngineer", "髙木悠人", "中央大学", "スライド"]
      }
  ]